gmnspy/__init__.py
gmnspy/in_out.py
gmnspy/schema.py
gmnspy/spec/geometry.schema.json
gmnspy/spec/gmns.spec.json
gmnspy/spec/lane.schema.json
gmnspy/spec/lane_tod.schema.json
gmnspy/spec/link.schema.json
gmnspy/spec/link_tod.schema.json
gmnspy/spec/location.schema.json
gmnspy/spec/movement.schema.json
gmnspy/spec/movement_tod.schema.json
gmnspy/spec/node.schema.json
gmnspy/spec/segment.schema.json
gmnspy/spec/segment_lane.schema.json
gmnspy/spec/segment_lane_tod.schema.json
gmnspy/spec/segment_tod.schema.json
gmnspy/spec/signal_controller.schema.json
gmnspy/spec/signal_coordination.schema.json
gmnspy/spec/signal_detector.schema.json
gmnspy/spec/signal_phase_mvmt.schema.json
gmnspy/spec/signal_timing_phase.schema.json
gmnspy/spec/signal_timing_plan.schema.json
gmnspy/spec/time_set_definitions.schema.json
gmnspy/spec/use_definition.schema.json
gmnspy/spec/use_group.schema.json
gmnspy/spec/zone.schema.json
gmnspy/utils/__init__.py
gmnspy/utils/list_to_md_table.py
gmnspy/utils/set_logger.py
gmnspy/validation/__init__.py
gmnspy/validation/constraint_checking.py
gmnspy/validation/foreign_keys.py
gmnspy/validation/required_files.py
gmnspy/validation/resources_existance.py
gmnspy/validation/schema_to_df.py
gmnspy-0.3.4.dist-info/LICENSE
gmnspy-0.3.4.dist-info/METADATA
gmnspy-0.3.4.dist-info/WHEEL
gmnspy-0.3.4.dist-info/top_level.txt
gmnspy-0.3.4.dist-info/RECORD
