Metadata-Version: 2.1
Name: gmnspy
Version: 0.3.4
Project-URL: Source, https://github.com/e-lo/GMNSpy
Project-URL: Homepage, https://e-lo.github.io/GMNSpy
Classifier: Development Status :: 3 - Alpha
License-File: LICENSE
Requires-Dist: frictionless
Requires-Dist: pandas >=1.0
